osuppy.cp36-win_amd64.pyd
osuppy-1.0.0.dist-info/METADATA
osuppy-1.0.0.dist-info/RECORD
osuppy-1.0.0.dist-info/WHEEL
osuppy-1.0.0.dist-info/top_level.txt
