Metadata-Version: 2.1
Name: osuppy
Version: 1.0.0
Summary: Library with tools to modify osu beatmap and database files.
Home-page: https://github.com/EgorDm/osupp
Author: Egor Dmitriev
Author-email: egordmitriev@gmail.com
License: MIT
Platform: UNKNOWN
Classifier: Programming Language :: Python :: 3
Classifier: License :: OSI Approved :: MIT License
